atlannot/__init__.py
atlannot/_atlalign.py
atlannot/displacements.py
atlannot/evaluation.py
atlannot/region_meta.py
atlannot/utils.py
atlannot/version.py
atlannot/ants/__init__.py
atlannot/atlas/__init__.py
atlannot/atlas/align.py
atlannot/merge/__init__.py
atlannot/merge/coarse.py
atlannot/merge/common.py
atlannot/merge/fine.py
atlannot/merge_original/JSONread.py
atlannot/merge_original/__init__.py
atlannot/merge_original/coarse.py
atlannot/merge_original/fine.py
atlannot/notebook/__init__.py
atlannot/notebook/util.py
atlannot/notebook/volume_viewer.py
atlannot-0.1.3.dist-info/AUTHORS.txt
atlannot-0.1.3.dist-info/LICENSE.txt
atlannot-0.1.3.dist-info/METADATA
atlannot-0.1.3.dist-info/WHEEL
atlannot-0.1.3.dist-info/top_level.txt
atlannot-0.1.3.dist-info/RECORD
