Metadata-Version: 2.1
Name: atlannot
Version: 0.1.3
Summary: Align and improve brain annotation atlases
Home-page: https://github.com/BlueBrain/atlas-annotation
Author: Blue Brain Project, EPFL
License: Apache-2.0
Project-URL: Source, https://github.com/BlueBrain/atlas-annotation
Project-URL: Tracker, https://github.com/BlueBrain/atlas-annotation/issues
Classifier: License :: OSI Approved :: Apache Software License
Classifier: Operating System :: Unix
Classifier: Operating System :: MacOS
Classifier: Programming Language :: Python :: 3.7
Classifier: Programming Language :: Python :: 3.8
Classifier: Programming Language :: Python :: 3.9
Requires-Python: >=3.7
License-File: LICENSE.txt
License-File: AUTHORS.txt
Requires-Dist: antspyx (>=0.2.7)
Requires-Dist: atldld (>=0.2.2)
Requires-Dist: matplotlib
Requires-Dist: numpy (>1.20)
Requires-Dist: pynrrd
Provides-Extra: data
Requires-Dist: dvc[ssh] (>=2) ; extra == 'data'
Provides-Extra: dev
Requires-Dist: bandit ; extra == 'dev'
Requires-Dist: black ; extra == 'dev'
Requires-Dist: flake8 ; extra == 'dev'
Requires-Dist: flake8-bugbear ; extra == 'dev'
Requires-Dist: flake8-comprehensions ; extra == 'dev'
Requires-Dist: flake8-docstrings ; extra == 'dev'
Requires-Dist: isort ; extra == 'dev'
Requires-Dist: pytest ; extra == 'dev'
Requires-Dist: pytest-cov ; extra == 'dev'
Requires-Dist: tox ; extra == 'dev'
Provides-Extra: docs
Requires-Dist: sphinx (>=1.3) ; extra == 'docs'
Requires-Dist: sphinx-bluebrain-theme ; extra == 'docs'
Provides-Extra: interactive
Requires-Dist: ipython ; extra == 'interactive'
Requires-Dist: ipywidgets ; extra == 'interactive'
Requires-Dist: nibabel ; extra == 'interactive'
Requires-Dist: scipy ; extra == 'interactive'
Requires-Dist: toml ; extra == 'interactive'
Requires-Dist: tqdm ; extra == 'interactive'
